<LocationRQ street-address-lookup="full" version="2.26" xmlns="http://skyhookwireless.com/wps/2005"><authentication version="2.2"><key key="eJwz5DQ0AAFLA2MLzmojMzcXIxNDR11LFxdTXQsDFwtdZ1MDY10nZ0NTU1NXR0cDY7daABFhCyk" username="7A2BED1FA277DAFCF1C9C76F47D24B44CFEEC531FDC2609BB57CB3FA4421852F" /></authentication><access-point><mac>84002d8789f0</mac><signal-strength>34</signal-strength></access-point><access-point><mac>46d9e791f554</mac><signal-strength>40</signal-strength></access-point><access-point><mac>84d47eb80580</mac><signal-strength>36</signal-strength></access-point><access-point><mac>068ddb6d413f</mac><signal-strength>56</signal-strength></access-point><access-point><mac>022722fa1b05</mac><signal-strength>36</signal-strength></access-point><access-point><mac>9a1554a8b008</mac><signal-strength>30</signal-strength></access-point><access-point><mac>8a1554a8af2a</mac><signal-strength>18</signal-strength></access-point><access-point><mac>c07cd1bc1f40</mac><signal-strength>22</signal-strength></access-point><access-point><mac>004e35193511</mac><signal-strength>68</signal-strength></access-point><access-point><mac>004e35193510</mac><signal-strength>68</signal-strength></access-point><access-point><mac>004e351886b1</mac><signal-strength>98</signal-strength></access-point><access-point><mac>004e351886b0</mac><signal-strength>98</signal-strength></access-point><access-point><mac>861554a8af2a</mac><signal-strength>26</signal-strength></access-point><access-point><mac>8e1554a9a620</mac><signal-strength>40</signal-strength></access-point><access-point><mac>8a1554a9a620</mac><signal-strength>38</signal-strength></access-point><access-point><mac>004e3517d4f1</mac><signal-strength>48</signal-strength></access-point><access-point><mac>004e3517d4f0</mac><signal-strength>48</signal-strength></access-point><access-point><mac>84d47eb81491</mac><signal-strength>30</signal-strength></access-point><access-point><mac>84d47eb81490</mac><signal-strength>30</signal-strength></access-point><access-point><mac>861554a8b008</mac><signal-strength>34</signal-strength></access-point><access-point><mac>8e1554a9a60e</mac><signal-strength>20</signal-strength></access-point><access-point><mac>004e351938d1</mac><signal-strength>54</signal-strength></access-point><access-point><mac>004e351938d0</mac><signal-strength>54</signal-strength></access-point><access-point><mac>004e351886a0</mac><signal-strength>110</signal-strength></access-point><access-point><mac>8adc96040050</mac><signal-strength>98</signal-strength></access-point><access-point><mac>004e35193500</mac><signal-strength>74</signal-strength></access-point><access-point><mac>88dc96040050</mac><signal-strength>90</signal-strength></access-point><access-point><mac>d45ddfc52f48</mac><signal-strength>64</signal-strength></access-point><access-point><mac>004e351938c1</mac><signal-strength>68</signal-strength></access-point><access-point><mac>004e351938c0</mac><signal-strength>68</signal-strength></access-point><access-point><mac>84002d8789f1</mac><signal-strength>34</signal-strength></access-point><access-point><mac>d45ddfc52f51</mac><signal-strength>40</signal-strength></access-point><access-point><mac>d45ddfc52f50</mac><signal-strength>40</signal-strength></access-point><access-point><mac>d45ddfc52f52</mac><signal-strength>42</signal-strength></access-point><access-point><mac>f29fc2354de9</mac><signal-strength>38</signal-strength></access-point><access-point><mac>004e351861b1</mac><signal-strength>134</signal-strength></access-point><access-point><mac>004e351861b0</mac><signal-strength>134</signal-strength></access-point><access-point><mac>8c0f6f925822</mac><signal-strength>38</signal-strength></access-point><access-point><mac>8c0f6f925821</mac><signal-strength>36</signal-strength></access-point><access-point><mac>8c0f6f925820</mac><signal-strength>36</signal-strength></access-point><access-point><mac>068dcb6d413f</mac><signal-strength>48</signal-strength></access-point><access-point><mac>0a8dcb6d413f</mac><signal-strength>48</signal-strength></access-point><access-point><mac>0e8dcb6d413f</mac><signal-strength>48</signal-strength></access-point><access-point><mac>1005016abed2</mac><signal-strength>64</signal-strength></access-point><access-point><mac>1005016abed1</mac><signal-strength>64</signal-strength></access-point><access-point><mac>1005016abed0</mac><signal-strength>64</signal-strength></access-point></LocationRQ>